{"57790251": {"highway": "turning_circle"}, "57806090": {"highway": "turning_circle"}, "57785421": {"highway": "turning_circle"}, "602421261": {"highway": "turning_circle"}, "57817924": {"highway": "turning_circle"}, "602889305": {"highway": "turning_circle"}, "57824013": {"highway": "turning_circle"}, "249041856": {"highway": "turning_circle"}, "262789989": {"highway": "turning_circle"}, "249041862": {"highway": "turning_circle"}, "57860981": {"highway": "turning_circle"}, "370893250": {"highway": "turning_circle"}, "57861959": {"highway": "turning_circle"}, "812885677": {"highway": "turning_circle"}, "57873070": {"highway": "turning_circle"}, "57877617": {"highway": "turning_circle"}, "57878669": {"highway": "turning_circle"}, "57882900": {"highway": "turning_circle"}, "57884371": {"highway": "turning_circle"}, "57861029": {"highway": "turning_circle"}, "57889854": {"highway": "turning_circle"}, "57891722": {"highway": "turning_circle"}, "249060100": {"highway": "turning_circle"}, "249041864": {"highway": "turning_circle"}, "2062799051": {"highway": "turning_circle"}, "301014791": {"highway": "turning_circle"}, "262294094": {"highway": "turning_circle"}, "57909485": {"highway": "turning_circle"}, "57910601": {"highway": "turning_circle"}, "57914926": {"highway": "turning_circle"}, "57916352": {"highway": "turning_circle"}, "541017861": {"highway": "turning_circle"}, "57922002": {"highway": "turning_circle"}, "57922522": {"highway": "turning_circle"}, "57931370": {"highway": "turning_circle"}, "262294262": {"highway": "turning_circle"}, "57954977": {"highway": "turning_circle"}, "57958098": {"highway": "turning_circle"}, "57960427": {"highway": "turning_circle"}, "65280672": {"highway": "turning_circle"}, "741740406": {"highway": "turning_circle"}, "65283028": {"highway": "turning_circle"}, "65286022": {"highway": "turning_circle"}, "65332667": {"highway": "turning_circle"}, "65286393": {"highway": "turning_circle"}, "65287193": {"highway": "turning_circle"}, "65289181": {"highway": "turning_circle"}, "65290696": {"highway": "turning_circle"}, "65290764": {"highway": "turning_circle"}, "65290867": {"highway": "turning_circle"}, "65291024": {"highway": "turning_circle"}, "65292830": {"highway": "turning_circle"}, "65294632": {"highway": "turning_circle"}, "65294782": {"highway": "turning_circle"}, "65294815": {"highway": "turning_circle"}, "65295607": {"highway": "turning_circle"}, "65295683": {"highway": "turning_circle"}, "1205459592": {"highway": "turning_circle"}, "65296157": {"highway": "turning_circle"}, "65297823": {"highway": "turning_circle"}, "65298214": {"highway": "turning_circle"}, "65298947": {"highway": "turning_circle"}, "65298962": {"highway": "turning_circle"}, "65299375": {"highway": "turning_circle"}, "65299721": {"highway": "turning_circle"}, "65301660": {"highway": "turning_circle"}, "65302590": {"highway": "turning_circle"}, "65302633": {"highway": "turning_circle"}, "65302861": {"highway": "turning_circle"}, "65303822": {"highway": "turning_circle"}, "65304045": {"highway": "turning_circle"}, "65305065": {"highway": "turning_circle"}, "253103147": {"highway": "turning_circle"}, "65305651": {"highway": "turning_circle"}, "65305723": {"highway": "turning_circle"}, "65305930": {"highway": "turning_circle"}, "65306909": {"highway": "turning_circle"}, "65307724": {"highway": "turning_circle"}, "65307920": {"highway": "turning_circle"}, "65308633": {"highway": "turning_circle"}, "65308946": {"highway": "turning_circle"}, "65310039": {"highway": "turning_circle"}, "65311848": {"highway": "turning_circle"}, "65312094": {"highway": "turning_circle"}, "65312736": {"highway": "turning_circle"}, "65313045": {"highway": "turning_circle"}, "65313067": {"highway": "turning_circle"}, "65313150": {"highway": "turning_circle"}, "65313411": {"highway": "turning_circle"}, "65313837": {"highway": "turning_circle"}, "356718341": {"highway": "turning_circle"}, "65315560": {"highway": "turning_circle"}, "65318263": {"highway": "turning_circle"}, "65320605": {"highway": "turning_circle"}, "65322390": {"highway": "turning_circle"}, "65323805": {"highway": "turning_circle"}, "313886091": {"highway": "turning_circle"}, "65324319": {"highway": "turning_circle"}, "65325177": {"highway": "turning_circle"}, "65325732": {"highway": "turning_circle"}, "65325902": {"highway": "turning_circle"}, "65325928": {"highway": "turning_circle"}, "65327334": {"highway": "turning_circle"}, "65328971": {"highway": "turning_circle"}, "65329838": {"highway": "turning_circle"}, "65329861": {"highway": "turning_circle"}, "65308534": {"highway": "turning_circle"}, "65330384": {"highway": "turning_circle"}, "65331005": {"highway": "turning_circle"}, "65332922": {"highway": "turning_circle"}, "65333311": {"highway": "turning_circle"}, "65333452": {"highway": "turning_circle"}, "65333503": {"highway": "turning_circle"}, "65335478": {"highway": "turning_circle"}, "65335491": {"highway": "turning_circle"}, "65335774": {"highway": "turning_circle"}, "65336541": {"highway": "turning_circle"}, "65336801": {"highway": "turning_circle"}, "65330498": {"highway": "turning_circle"}, "65337580": {"highway": "turning_circle"}, "65337772": {"highway": "turning_circle"}, "65341593": {"highway": "turning_circle"}, "65342425": {"highway": "turning_circle"}, "65342696": {"highway": "turning_circle"}, "65343085": {"highway": "turning_circle"}, "65345415": {"highway": "turning_circle"}, "65345559": {"highway": "turning_circle"}, "65345592": {"highway": "turning_circle"}, "65345732": {"highway": "turning_circle"}, "65346008": {"highway": "turning_circle"}, "767834405": {"highway": "turning_circle"}, "65346721": {"highway": "turning_circle"}, "65346791": {"highway": "turning_circle"}, "65347421": {"highway": "turning_circle"}, "259428910": {"highway": "turning_circle"}, "65347819": {"highway": "turning_circle"}, "65348185": {"highway": "turning_circle"}, "342552112": {"highway": "turning_circle"}, "65348511": {"highway": "turning_circle"}, "65348845": {"highway": "turning_circle"}, "65349142": {"highway": "turning_circle"}, "65349144": {"highway": "turning_circle"}, "601342298": {"highway": "turning_circle"}, "65349444": {"highway": "turning_circle"}, "65349731": {"highway": "turning_circle"}, "615405952": {"highway": "turning_circle"}, "65350431": {"highway": "turning_circle"}, "65350464": {"highway": "turning_circle"}, "65350943": {"highway": "turning_circle"}, "65351478": {"highway": "turning_circle"}, "65351737": {"highway": "turning_circle"}, "65351953": {"highway": "turning_circle"}, "539989862": {"highway": "turning_circle"}, "65352503": {"highway": "turning_circle"}, "287838782": {"highway": "turning_circle"}, "65354188": {"highway": "turning_circle"}, "65354274": {"highway": "turning_circle"}, "65354511": {"highway": "turning_circle"}, "65355162": {"highway": "turning_circle"}, "65356928": {"highway": "turning_circle"}, "65356994": {"highway": "turning_circle"}, "65357285": {"highway": "turning_circle"}, "65357584": {"highway": "turning_circle"}, "65357696": {"highway": "turning_circle"}, "253124665": {"highway": "turning_circle"}, "437601656": {"highway": "turning_circle"}, "65358902": {"highway": "turning_circle"}, "65359004": {"highway": "turning_circle"}, "65361006": {"highway": "turning_circle"}, "65361818": {"highway": "turning_circle"}, "65362282": {"highway": "turning_circle"}, "297858360": {"highway": "turning_circle"}, "615278344": {"highway": "turning_circle"}, "65365356": {"highway": "turning_circle"}, "65366518": {"highway": "turning_circle"}, "65366527": {"highway": "turning_circle"}, "65366817": {"highway": "turning_circle"}, "65369521": {"highway": "turning_circle"}, "65370802": {"highway": "turning_circle"}, "65370809": {"highway": "turning_circle"}, "65371080": {"highway": "turning_circle"}, "65371464": {"highway": "turning_circle"}, "2317760294": {"highway": "turning_circle"}, "65373094": {"highway": "turning_circle"}, "65373535": {"highway": "turning_circle"}, "65373786": {"highway": "turning_circle"}, "65373987": {"highway": "turning_circle"}, "65385086": {"highway": "turning_circle"}, "65388795": {"highway": "turning_circle"}, "342601632": {"highway": "turning_circle"}, "65388995": {"highway": "turning_circle"}, "65389231": {"highway": "turning_circle"}, "65389367": {"highway": "turning_circle"}, "65389703": {"highway": "turning_circle"}, "65390042": {"highway": "turning_circle"}, "65390221": {"highway": "turning_circle"}, "65390390": {"highway": "turning_circle"}, "437899797": {"highway": "turning_circle"}, "65390815": {"highway": "turning_circle"}, "262934295": {"highway": "turning_circle"}, "65391106": {"highway": "turning_circle"}, "65391300": {"highway": "turning_circle"}, "65391556": {"highway": "turning_circle"}, "361074800": {"highway": "turning_circle"}, "65392447": {"highway": "turning_circle"}, "65392467": {"highway": "turning_circle"}, "418089428": {"highway": "turning_circle"}, "535529320": {"highway": "turning_circle"}, "65393272": {"highway": "turning_circle"}, "65393304": {"highway": "turning_circle"}, "65393315": {"highway": "turning_circle"}, "65393414": {"highway": "turning_circle"}, "65393473": {"highway": "turning_circle"}, "65393855": {"highway": "turning_circle"}, "65394069": {"highway": "turning_circle"}, "65391664": {"highway": "turning_circle"}, "65395397": {"highway": "turning_circle"}, "65395422": {"highway": "turning_circle"}, "65395437": {"highway": "turning_circle"}, "65395497": {"highway": "turning_circle"}, "65395582": {"highway": "turning_circle"}, "360982277": {"highway": "turning_circle"}, "65395755": {"highway": "turning_circle"}, "65395761": {"highway": "turning_circle"}, "65395901": {"highway": "turning_circle"}, "65395999": {"highway": "turning_circle"}, "65396276": {"highway": "turning_circle"}, "65396280": {"highway": "turning_circle"}, "65396514": {"highway": "turning_circle"}, "65396954": {"highway": "turning_circle"}, "65396963": {"highway": "turning_circle"}, "65396971": {"highway": "turning_circle"}, "65397204": {"highway": "turning_circle"}, "250027151": {"highway": "turning_circle"}, "65397664": {"highway": "turning_circle"}, "173245861": {"highway": "turning_circle"}, "65398836": {"highway": "turning_circle"}, "65400148": {"highway": "turning_circle"}, "65400348": {"highway": "turning_circle"}, "65400723": {"highway": "turning_circle"}, "65400742": {"highway": "turning_circle"}, "360896508": {"highway": "turning_circle"}, "365778961": {"highway": "turning_circle"}, "65400950": {"highway": "turning_circle"}, "65401097": {"highway": "turning_circle"}, "173241188": {"highway": "turning_circle"}, "65401793": {"highway": "turning_circle"}, "271267458": {"highway": "turning_circle"}, "65403193": {"highway": "turning_circle"}, "65403419": {"highway": "turning_circle"}, "65403658": {"highway": "turning_circle"}, "65404243": {"highway": "turning_circle"}, "65404278": {"highway": "turning_circle"}, "65404290": {"highway": "turning_circle"}, "65404427": {"highway": "turning_circle"}, "65405250": {"highway": "turning_circle"}, "271267208": {"highway": "turning_circle"}, "65405310": {"highway": "turning_circle"}, "418582481": {"highway": "turning_circle"}, "335614355": {"highway": "turning_circle"}, "65405652": {"highway": "turning_circle"}, "65406073": {"highway": "turning_circle"}, "65406189": {"highway": "turning_circle"}, "65406413": {"highway": "turning_circle"}, "65406548": {"highway": "turning_circle"}, "65407538": {"highway": "turning_circle"}, "360976379": {"highway": "turning_circle"}, "65408388": {"highway": "turning_circle"}, "65408418": {"highway": "turning_circle"}, "2374614352": {"highway": "turning_circle"}, "65409044": {"highway": "turning_circle"}, "65409047": {"highway": "turning_circle"}, "65409311": {"highway": "turning_circle"}, "65409330": {"highway": "turning_circle"}, "65410592": {"highway": "turning_circle"}, "65410682": {"highway": "turning_circle"}, "2374614396": {"highway": "turning_circle"}, "65411783": {"highway": "turning_circle"}, "65411808": {"highway": "turning_circle"}, "65411829": {"highway": "turning_circle"}, "65411895": {"highway": "turning_circle"}, "365779141": {"highway": "turning_circle"}, "65384613": {"highway": "turning_circle"}, "262917126": {"highway": "turning_circle"}, "65413247": {"highway": "turning_circle"}, "65413269": {"highway": "turning_circle"}, "65413272": {"highway": "turning_circle"}, "65413469": {"highway": "turning_circle"}, "65413737": {"highway": "turning_circle"}, "65413881": {"highway": "turning_circle"}, "65413917": {"highway": "turning_circle"}, "3931865760": {"highway": "turning_circle"}, "259426238": {"highway": "turning_circle"}, "65414400": {"highway": "turning_circle"}, "65414553": {"highway": "turning_circle"}, "65414555": {"highway": "turning_circle"}, "65414878": {"highway": "turning_circle"}, "65415155": {"highway": "turning_circle"}, "2374614343": {"highway": "turning_circle"}, "65416050": {"highway": "turning_circle"}, "65416417": {"highway": "turning_circle"}, "437894472": {"highway": "turning_circle"}, "65416934": {"highway": "turning_circle"}, "65416945": {"highway": "turning_circle"}, "65417033": {"highway": "turning_circle"}, "65417555": {"highway": "turning_circle"}, "410836771": {"highway": "turning_circle"}, "65418654": {"highway": "turning_circle"}, "65418659": {"highway": "turning_circle"}, "65418665": {"highway": "turning_circle"}, "65418670": {"highway": "turning_circle"}, "359008135": {"highway": "turning_circle"}, "65419106": {"highway": "turning_circle"}, "338892410": {"highway": "turning_circle"}, "65419766": {"highway": "turning_circle"}, "437904346": {"highway": "turning_circle"}, "65420282": {"highway": "turning_circle"}, "361134980": {"highway": "turning_circle"}, "65420388": {"highway": "turning_circle"}, "437895950": {"highway": "turning_circle"}, "65420474": {"highway": "turning_circle"}, "65421104": {"highway": "turning_circle"}, "65421642": {"highway": "turning_circle"}, "65422166": {"highway": "turning_circle"}, "65422667": {"highway": "turning_circle"}, "338890442": {"highway": "turning_circle"}, "65423870": {"highway": "turning_circle"}, "65423880": {"highway": "turning_circle"}, "65424220": {"highway": "turning_circle"}, "65424240": {"highway": "turning_circle"}, "65424511": {"highway": "turning_circle"}, "65424513": {"highway": "turning_circle"}, "65424533": {"highway": "turning_circle"}, "420501812": {"highway": "turning_circle"}, "65426371": {"highway": "turning_circle"}, "391717793": {"highway": "turning_circle"}, "65426421": {"highway": "turning_circle"}, "65426475": {"highway": "turning_circle"}, "65426642": {"highway": "turning_circle"}, "65426870": {"highway": "turning_circle"}, "65427657": {"highway": "turning_circle"}, "65427832": {"highway": "turning_circle"}, "260335661": {"highway": "turning_circle"}, "65428081": {"highway": "turning_circle"}, "65428267": {"highway": "turning_circle"}, "65428297": {"highway": "turning_circle"}, "65428305": {"highway": "turning_circle"}, "65428319": {"highway": "turning_circle"}, "65428364": {"highway": "turning_circle"}, "65428653": {"highway": "turning_circle"}, "65429187": {"highway": "turning_circle"}, "412094243": {"highway": "turning_circle"}, "65429275": {"highway": "turning_circle"}, "65429824": {"highway": "turning_circle"}, "318206823": {"highway": "turning_circle"}, "267292526": {"highway": "turning_circle"}, "65429880": {"highway": "turning_circle"}, "65430061": {"highway": "turning_circle"}, "65430316": {"highway": "turning_circle"}, "436125341": {"highway": "turning_circle"}, "65431066": {"highway": "turning_circle"}, "65431419": {"highway": "turning_circle"}, "2375870900": {"highway": "turning_circle"}, "297418381": {"highway": "turning_circle"}, "65431918": {"highway": "turning_circle"}, "65432019": {"highway": "turning_circle"}, "65432093": {"highway": "turning_circle"}, "65432136": {"highway": "turning_circle"}, "436869923": {"highway": "turning_circle"}, "65433534": {"highway": "turning_circle"}, "65434258": {"highway": "turning_circle"}, "338888199": {"highway": "turning_circle"}, "65434473": {"highway": "turning_circle"}, "65434498": {"highway": "turning_circle"}, "65434505": {"highway": "turning_circle"}, "259577744": {"highway": "turning_circle"}, "65434630": {"highway": "turning_circle"}, "65435248": {"highway": "turning_circle"}, "65435352": {"highway": "turning_circle"}, "65435403": {"highway": "turning_circle"}, "286095504": {"highway": "turning_circle"}, "253135780": {"highway": "turning_circle"}, "452931901": {"highway": "turning_circle"}, "65436445": {"highway": "turning_circle"}, "263573252": {"highway": "turning_circle"}, "65436638": {"highway": "turning_circle"}, "391749638": {"highway": "turning_circle"}, "252345122": {"highway": "turning_circle"}, "65436865": {"highway": "turning_circle"}, "65436946": {"highway": "turning_circle"}, "65436950": {"highway": "turning_circle"}, "65436982": {"highway": "turning_circle"}, "257492994": {"highway": "turning_circle"}, "452361147": {"highway": "turning_circle"}, "65437871": {"highway": "turning_circle"}, "65438547": {"highway": "turning_circle"}, "305052271": {"highway": "turning_circle"}, "339268482": {"highway": "turning_circle"}, "65439635": {"highway": "turning_circle"}, "65439643": {"highway": "turning_circle"}, "65439655": {"highway": "turning_circle"}, "65439861": {"highway": "turning_circle"}, "65439957": {"highway": "turning_circle"}, "418089425": {"highway": "turning_circle"}, "65440836": {"highway": "turning_circle"}, "65440841": {"highway": "turning_circle"}, "65441099": {"highway": "turning_circle"}, "65441873": {"highway": "turning_circle"}, "65441960": {"highway": "turning_circle"}, "65441991": {"highway": "turning_circle"}, "65442001": {"highway": "turning_circle"}, "65442257": {"highway": "turning_circle"}, "65443735": {"highway": "turning_circle"}, "266658644": {"highway": "turning_circle"}, "65444556": {"highway": "turning_circle"}, "338888393": {"highway": "turning_circle"}, "65444639": {"highway": "turning_circle"}, "413326038": {"highway": "turning_circle"}, "253090206": {"highway": "turning_circle"}, "65445183": {"highway": "turning_circle"}, "65445295": {"highway": "turning_circle"}, "260335664": {"highway": "turning_circle"}, "65445536": {"highway": "turning_circle"}, "262078576": {"highway": "turning_circle"}, "65446528": {"highway": "turning_circle"}, "65447187": {"highway": "turning_circle"}, "65447279": {"highway": "turning_circle"}, "65390484": {"highway": "turning_circle"}, "65447745": {"highway": "turning_circle"}, "441573039": {"highway": "turning_circle"}, "65447975": {"highway": "turning_circle"}, "426079032": {"highway": "turning_circle"}, "65448917": {"highway": "turning_circle"}, "65448937": {"highway": "turning_circle"}, "313865109": {"highway": "turning_circle"}, "65449129": {"highway": "turning_circle"}, "65449466": {"highway": "turning_circle"}, "65449517": {"highway": "turning_circle"}, "65449597": {"highway": "turning_circle"}, "65449681": {"highway": "turning_circle"}, "65449749": {"highway": "turning_circle"}, "65449814": {"highway": "turning_circle"}, "250042014": {"highway": "turning_circle"}, "65450389": {"highway": "turning_circle"}, "65450390": {"highway": "turning_circle"}, "65450576": {"highway": "turning_circle"}, "65450785": {"highway": "turning_circle"}, "65450925": {"highway": "turning_circle"}, "65451138": {"highway": "turning_circle"}, "266994679": {"highway": "turning_circle"}, "65451726": {"highway": "turning_circle"}, "260335734": {"highway": "turning_circle"}, "506108010": {"highway": "turning_circle"}, "253140468": {"highway": "turning_circle"}, "412375241": {"highway": "turning_circle"}, "65452974": {"highway": "turning_circle"}, "65452976": {"highway": "turning_circle"}, "65454245": {"highway": "turning_circle"}, "441304178": {"highway": "turning_circle"}, "65454377": {"highway": "turning_circle"}, "65454645": {"highway": "turning_circle"}, "65454887": {"highway": "turning_circle"}, "318792232": {"highway": "turning_circle"}, "65455601": {"highway": "turning_circle"}, "65455723": {"highway": "turning_circle"}, "257495480": {"highway": "turning_circle"}, "65456325": {"highway": "turning_circle"}, "253099558": {"highway": "turning_circle"}, "65456646": {"highway": "turning_circle"}, "65456776": {"highway": "turning_circle"}, "65456778": {"highway": "turning_circle"}, "65457330": {"highway": "turning_circle"}, "65457636": {"highway": "turning_circle"}, "65457746": {"highway": "turning_circle"}, "65457926": {"highway": "turning_circle"}, "65458182": {"highway": "turning_circle"}, "304836877": {"highway": "turning_circle"}, "262934600": {"highway": "turning_circle"}, "314134148": {"highway": "turning_circle"}, "418088965": {"highway": "turning_circle"}, "259168450": {"highway": "turning_circle"}, "621201586": {"highway": "turning_circle"}, "65459679": {"highway": "turning_circle"}, "253141460": {"highway": "turning_circle"}, "65460248": {"highway": "turning_circle"}, "65460436": {"highway": "turning_circle"}, "65460478": {"highway": "turning_circle"}, "65460485": {"highway": "turning_circle"}, "410838804": {"highway": "turning_circle"}, "65460652": {"highway": "turning_circle"}, "65460887": {"highway": "turning_circle"}, "65462379": {"highway": "turning_circle"}, "267292637": {"highway": "turning_circle"}, "65462962": {"highway": "turning_circle"}, "262934627": {"highway": "turning_circle"}, "65463424": {"highway": "turning_circle"}, "65463443": {"highway": "turning_circle"}, "452360778": {"highway": "turning_circle"}, "452360776": {"highway": "turning_circle"}, "65463942": {"highway": "turning_circle"}, "65463990": {"highway": "turning_circle"}, "297419374": {"highway": "turning_circle"}, "360984126": {"highway": "turning_circle"}, "65464195": {"highway": "turning_circle"}, "267292155": {"highway": "turning_circle"}, "65464580": {"highway": "turning_circle"}, "65464870": {"highway": "turning_circle"}, "65464942": {"highway": "turning_circle"}, "65465154": {"highway": "turning_circle"}, "65465685": {"highway": "turning_circle"}, "65465711": {"highway": "turning_circle"}, "65465749": {"highway": "turning_circle"}, "65465779": {"highway": "turning_circle"}, "65465786": {"highway": "turning_circle"}, "261559653": {"highway": "turning_circle"}, "65466207": {"highway": "turning_circle"}, "65466214": {"highway": "turning_circle"}, "65466397": {"highway": "turning_circle"}, "173244087": {"highway": "turning_circle"}, "65466498": {"highway": "turning_circle"}, "65466574": {"highway": "turning_circle"}, "65466647": {"highway": "turning_circle"}, "65466795": {"highway": "turning_circle"}, "65466843": {"highway": "turning_circle"}, "65466872": {"highway": "turning_circle"}, "262934540": {"highway": "turning_circle"}, "65467391": {"highway": "turning_circle"}, "65467422": {"highway": "turning_circle"}, "65467450": {"highway": "turning_circle"}, "65467453": {"highway": "turning_circle"}, "65467473": {"highway": "turning_circle"}, "65467620": {"highway": "turning_circle"}, "65468163": {"highway": "turning_circle"}, "65468170": {"highway": "turning_circle"}, "262916572": {"highway": "turning_circle"}, "65468565": {"highway": "turning_circle"}, "318306393": {"highway": "turning_circle"}, "65468834": {"highway": "turning_circle"}, "65469130": {"highway": "turning_circle"}, "65469324": {"highway": "turning_circle"}, "65469419": {"highway": "turning_circle"}, "65469981": {"highway": "turning_circle"}, "65470078": {"highway": "turning_circle"}, "65470222": {"highway": "turning_circle"}, "65470507": {"highway": "turning_circle"}, "65470882": {"highway": "turning_circle"}, "65471285": {"highway": "turning_circle"}, "65471646": {"highway": "turning_circle"}, "65471728": {"highway": "turning_circle"}, "65472094": {"highway": "turning_circle"}, "262934648": {"highway": "turning_circle"}, "267469852": {"highway": "turning_circle"}, "65472216": {"highway": "turning_circle"}, "65472226": {"highway": "turning_circle"}, "65472726": {"highway": "turning_circle"}, "65472754": {"highway": "turning_circle"}, "65473722": {"highway": "turning_circle"}, "65474213": {"highway": "turning_circle"}, "65474277": {"highway": "turning_circle"}, "65474492": {"highway": "turning_circle"}, "65475550": {"highway": "turning_circle"}, "65475863": {"highway": "turning_circle"}, "65476311": {"highway": "turning_circle"}, "65477165": {"highway": "turning_circle"}, "253090205": {"highway": "turning_circle"}, "65477932": {"highway": "turning_circle"}, "65478075": {"highway": "turning_circle"}, "65478162": {"highway": "turning_circle"}, "65478202": {"highway": "turning_circle"}, "65478220": {"highway": "turning_circle"}, "65478401": {"highway": "turning_circle"}, "452360297": {"highway": "turning_circle"}, "65479347": {"highway": "turning_circle"}, "65479382": {"highway": "turning_circle"}, "418575211": {"highway": "turning_circle"}, "65479862": {"highway": "turning_circle"}, "65479875": {"highway": "turning_circle"}, "420522698": {"highway": "turning_circle"}, "65480248": {"highway": "turning_circle"}, "65480401": {"highway": "turning_circle"}, "65480572": {"highway": "turning_circle"}, "426319694": {"highway": "turning_circle"}, "65481645": {"highway": "turning_circle"}, "65482204": {"highway": "turning_circle"}, "65482324": {"highway": "turning_circle"}, "529897221": {"highway": "turning_circle"}, "65482839": {"highway": "turning_circle"}, "65482857": {"highway": "turning_circle"}, "65483560": {"highway": "turning_circle"}, "65483662": {"highway": "turning_circle"}, "65483676": {"highway": "turning_circle"}, "65483689": {"highway": "turning_circle"}, "338886410": {"highway": "turning_circle"}, "65483986": {"highway": "turning_circle"}, "65484011": {"highway": "turning_circle"}, "65484573": {"highway": "turning_circle"}, "65484715": {"highway": "turning_circle"}, "65484768": {"highway": "turning_circle"}, "413326537": {"highway": "turning_circle"}, "65485659": {"highway": "turning_circle"}, "65485771": {"highway": "turning_circle"}, "361061571": {"highway": "turning_circle"}, "65485967": {"highway": "turning_circle"}, "65486188": {"highway": "turning_circle"}, "65487830": {"highway": "turning_circle"}, "65487876": {"highway": "turning_circle"}, "65487948": {"highway": "turning_circle"}, "65488107": {"highway": "turning_circle"}, "65488116": {"highway": "turning_circle"}, "410836689": {"highway": "turning_circle"}, "65488277": {"highway": "turning_circle"}, "260335731": {"highway": "turning_circle"}, "65488336": {"highway": "turning_circle"}, "65488593": {"highway": "turning_circle"}, "410830210": {"highway": "turning_circle"}, "65488637": {"highway": "turning_circle"}, "65488725": {"highway": "turning_circle"}, "65488826": {"highway": "turning_circle"}, "65488910": {"highway": "turning_circle"}, "65488989": {"highway": "turning_circle"}, "65489206": {"highway": "turning_circle"}, "65489255": {"highway": "turning_circle"}, "65489273": {"highway": "turning_circle"}, "418580395": {"highway": "turning_circle"}, "441303490": {"highway": "turning_circle"}, "65490897": {"highway": "turning_circle"}, "65491602": {"highway": "turning_circle"}, "65491861": {"highway": "turning_circle"}, "65491870": {"highway": "turning_circle"}, "65492372": {"highway": "turning_circle"}, "65492380": {"highway": "turning_circle"}, "65492606": {"highway": "turning_circle"}, "420501734": {"highway": "turning_circle"}, "65492968": {"highway": "turning_circle"}, "65493018": {"highway": "turning_circle"}, "65493249": {"highway": "turning_circle"}, "65493300": {"highway": "turning_circle"}, "65493398": {"highway": "turning_circle"}, "65493400": {"highway": "turning_circle"}, "65493429": {"highway": "turning_circle"}, "65493645": {"highway": "turning_circle"}, "65493961": {"highway": "turning_circle"}, "259587978": {"highway": "turning_circle"}, "529895147": {"highway": "turning_circle"}, "529895131": {"highway": "turning_circle"}, "65494956": {"highway": "turning_circle"}, "65495013": {"highway": "turning_circle"}, "65495065": {"highway": "turning_circle"}, "365779391": {"highway": "turning_circle"}, "259428970": {"highway": "turning_circle"}, "351962977": {"highway": "turning_circle"}, "65495553": {"highway": "turning_circle"}, "65495816": {"highway": "turning_circle"}, "65495979": {"highway": "turning_circle"}, "65496041": {"highway": "turning_circle"}, "420501712": {"highway": "turning_circle"}, "65496189": {"highway": "turning_circle"}, "65496217": {"highway": "turning_circle"}, "65496445": {"highway": "turning_circle"}, "360897223": {"highway": "turning_circle"}, "65496639": {"highway": "turning_circle"}, "341597911": {"highway": "turning_circle"}, "65496843": {"highway": "turning_circle"}, "65497622": {"highway": "turning_circle"}, "260397399": {"highway": "turning_circle"}, "65498104": {"highway": "turning_circle"}, "65498504": {"highway": "turning_circle"}, "65498606": {"highway": "turning_circle"}, "65498827": {"highway": "turning_circle"}, "452359919": {"highway": "turning_circle"}, "65499106": {"highway": "turning_circle"}, "65499130": {"highway": "turning_circle"}, "65499554": {"highway": "turning_circle"}, "65499600": {"highway": "turning_circle"}, "65499607": {"highway": "turning_circle"}, "65499839": {"highway": "turning_circle"}, "65499852": {"highway": "turning_circle"}, "65500214": {"highway": "turning_circle"}, "418118880": {"highway": "turning_circle"}, "65500403": {"highway": "turning_circle"}, "318210521": {"highway": "turning_circle"}, "435189845": {"highway": "turning_circle"}, "65500627": {"highway": "turning_circle"}, "65500742": {"highway": "turning_circle"}, "65501395": {"highway": "turning_circle"}, "65501537": {"highway": "turning_circle"}, "65501635": {"highway": "turning_circle"}, "65502531": {"highway": "turning_circle"}, "65502731": {"highway": "turning_circle"}, "65502742": {"highway": "turning_circle"}, "259578035": {"highway": "turning_circle"}, "65503320": {"highway": "turning_circle"}, "65503384": {"highway": "turning_circle"}, "65503444": {"highway": "turning_circle"}, "418089426": {"highway": "turning_circle"}, "262909431": {"highway": "turning_circle"}, "452363382": {"highway": "turning_circle"}, "65503774": {"highway": "turning_circle"}, "529897172": {"highway": "turning_circle"}, "65503949": {"highway": "turning_circle"}, "65503992": {"highway": "turning_circle"}, "65504204": {"highway": "turning_circle"}, "65504503": {"highway": "turning_circle"}, "259426898": {"highway": "turning_circle"}, "65505317": {"highway": "turning_circle"}, "293847089": {"highway": "turning_circle"}, "65505624": {"highway": "turning_circle"}, "65505789": {"highway": "turning_circle"}, "263958054": {"highway": "turning_circle"}, "65506112": {"highway": "turning_circle"}, "65506169": {"highway": "turning_circle"}, "250042792": {"highway": "turning_circle"}, "65506455": {"highway": "turning_circle"}, "65506564": {"highway": "turning_circle"}, "2374614383": {"highway": "turning_circle"}, "437920728": {"highway": "turning_circle"}, "65507293": {"highway": "turning_circle"}, "65507428": {"highway": "turning_circle"}, "65507434": {"highway": "turning_circle"}, "65507444": {"highway": "turning_circle"}, "266640144": {"highway": "turning_circle"}, "262909623": {"highway": "turning_circle"}, "65507755": {"highway": "turning_circle"}, "65507822": {"highway": "turning_circle"}, "529895136": {"highway": "turning_circle"}, "65509070": {"highway": "turning_circle"}, "65509078": {"highway": "turning_circle"}, "413326580": {"highway": "turning_circle"}, "621201548": {"highway": "turning_circle"}, "65511054": {"highway": "turning_circle"}, "621201549": {"highway": "turning_circle"}, "65509798": {"highway": "turning_circle"}, "426321241": {"highway": "turning_circle"}, "621201553": {"highway": "turning_circle"}, "65511053": {"highway": "turning_circle"}, "65510552": {"highway": "turning_circle"}, "65510923": {"highway": "turning_circle"}, "65511471": {"highway": "turning_circle"}, "65511823": {"highway": "turning_circle"}, "305533352": {"highway": "turning_circle"}, "65511894": {"highway": "turning_circle"}, "65511899": {"highway": "turning_circle"}, "65512039": {"highway": "turning_circle"}, "252346670": {"highway": "turning_circle"}, "259168411": {"highway": "turning_circle"}, "1157558997": {"highway": "turning_circle"}, "259577298": {"highway": "turning_circle"}, "65513924": {"highway": "turning_circle"}, "65513966": {"highway": "turning_circle"}, "65514117": {"highway": "turning_circle"}, "65514612": {"highway": "turning_circle"}, "260301593": {"highway": "turning_circle"}, "65514857": {"highway": "turning_circle"}, "65514861": {"highway": "turning_circle"}, "65514903": {"highway": "turning_circle"}, "65514911": {"highway": "turning_circle"}, "65515103": {"highway": "turning_circle"}, "260433608": {"highway": "turning_circle"}, "65515351": {"highway": "turning_circle"}, "296886255": {"highway": "turning_circle"}, "410828217": {"highway": "turning_circle"}, "65515569": {"highway": "turning_circle"}, "65515623": {"highway": "turning_circle"}, "301183493": {"highway": "turning_circle"}, "418582644": {"highway": "turning_circle"}, "65515872": {"highway": "turning_circle"}, "65515885": {"highway": "turning_circle"}, "65516094": {"highway": "turning_circle"}, "65516127": {"highway": "turning_circle"}, "65516208": {"highway": "turning_circle"}, "65516292": {"highway": "turning_circle"}, "259168545": {"highway": "turning_circle"}, "65516836": {"highway": "turning_circle"}, "65517410": {"highway": "turning_circle"}, "65517420": {"highway": "turning_circle"}, "256819936": {"highway": "turning_circle"}, "65517561": {"highway": "turning_circle"}, "65517568": {"highway": "turning_circle"}, "65517636": {"highway": "turning_circle"}, "297418560": {"highway": "turning_circle"}, "65517928": {"highway": "turning_circle"}, "65518089": {"highway": "turning_circle"}, "65518114": {"highway": "turning_circle"}, "338888444": {"highway": "turning_circle"}, "65518175": {"highway": "turning_circle"}, "65518391": {"highway": "turning_circle"}, "65518438": {"highway": "turning_circle"}, "65519296": {"highway": "turning_circle"}, "65519574": {"highway": "turning_circle"}, "65519580": {"highway": "turning_circle"}, "65519617": {"highway": "turning_circle"}, "260321897": {"highway": "turning_circle"}, "65519993": {"highway": "turning_circle"}, "65520040": {"highway": "turning_circle"}, "65520780": {"highway": "turning_circle"}, "260451195": {"highway": "turning_circle"}, "65520874": {"highway": "turning_circle"}, "65520953": {"highway": "turning_circle"}, "65520967": {"highway": "turning_circle"}, "65520971": {"highway": "turning_circle"}, "351088799": {"highway": "turning_circle"}, "271267436": {"highway": "turning_circle"}, "418582568": {"highway": "turning_circle"}, "65522214": {"highway": "turning_circle"}, "65522227": {"highway": "turning_circle"}, "65522354": {"highway": "turning_circle"}, "259578095": {"highway": "turning_circle"}, "65522486": {"highway": "turning_circle"}, "65522550": {"highway": "turning_circle"}, "65522701": {"highway": "turning_circle"}, "452361532": {"highway": "turning_circle"}, "65522765": {"highway": "turning_circle"}, "65522942": {"highway": "turning_circle"}, "92833359": {"highway": "turning_circle"}, "65339600": {"highway": "turning_circle"}, "65352567": {"highway": "turning_circle"}, "2587869089": {"highway": "turning_circle"}, "368391094": {"highway": "turning_circle"}, "110378241": {"highway": "turning_circle"}, "110380859": {"highway": "turning_circle"}, "110382671": {"highway": "turning_circle"}, "339283196": {"highway": "turning_circle"}, "110386184": {"highway": "turning_circle"}, "110386234": {"highway": "turning_circle"}, "258641163": {"highway": "turning_circle"}, "1075474252": {"highway": "turning_circle"}, "110394387": {"highway": "turning_circle"}, "110398465": {"highway": "turning_circle"}, "110401569": {"highway": "turning_circle"}, "110405069": {"highway": "turning_circle"}, "110408492": {"highway": "turning_circle"}, "110410006": {"highway": "turning_circle"}, "110414793": {"highway": "turning_circle"}, "258645663": {"highway": "turning_circle"}, "110416454": {"highway": "turning_circle"}, "414921941": {"highway": "turning_circle"}, "110417641": {"highway": "turning_circle"}, "110418337": {"highway": "turning_circle"}, "110418508": {"highway": "turning_circle"}, "110421129": {"highway": "turning_circle"}, "1075678565": {"highway": "turning_circle"}, "110426629": {"highway": "turning_circle"}, "110427588": {"highway": "turning_circle"}, "110428064": {"highway": "turning_circle"}, "315461387": {"highway": "turning_circle"}, "110430686": {"highway": "turning_circle"}, "110431319": {"highway": "turning_circle"}, "110432751": {"highway": "turning_circle"}, "110434372": {"highway": "turning_circle"}, "110436091": {"highway": "turning_circle"}, "339304989": {"highway": "turning_circle"}, "258632146": {"highway": "turning_circle"}, "110438442": {"highway": "turning_circle"}, "1075505292": {"highway": "turning_circle"}, "110440749": {"highway": "turning_circle"}, "110441269": {"highway": "turning_circle"}, "110441381": {"highway": "turning_circle"}, "110441458": {"highway": "turning_circle"}, "414732966": {"highway": "turning_circle"}, "110443389": {"highway": "turning_circle"}, "110443499": {"highway": "turning_circle"}, "110444002": {"highway": "turning_circle"}, "2286860871": {"highway": "turning_circle"}, "414921930": {"highway": "turning_circle"}, "110445629": {"highway": "turning_circle"}, "1057503001": {"highway": "turning_circle"}, "110448605": {"highway": "turning_circle"}, "1075497540": {"highway": "turning_circle"}, "414733286": {"highway": "turning_circle"}, "110412792": {"highway": "turning_circle"}, "110455245": {"highway": "turning_circle"}, "110456326": {"highway": "turning_circle"}, "110458234": {"highway": "turning_circle"}, "414900025": {"highway": "turning_circle"}, "110460336": {"highway": "turning_circle"}, "110460412": {"highway": "turning_circle"}, "1060155085": {"highway": "turning_circle"}, "110462992": {"highway": "turning_circle"}, "1152416951": {"highway": "turning_circle"}, "110465127": {"highway": "turning_circle"}, "258631304": {"highway": "turning_circle"}, "110466208": {"highway": "turning_circle"}, "4772756161": {"highway": "turning_circle"}, "57917568": {"highway": "turning_circle"}, "418582993": {"highway": "turning_circle"}, "253106505": {"highway": "turning_circle"}, "253139586": {"highway": "turning_circle"}, "253139641": {"highway": "turning_circle"}, "410827611": {"highway": "turning_circle"}, "257292747": {"highway": "turning_circle"}, "257292913": {"highway": "turning_circle"}, "65471300": {"highway": "turning_circle"}, "331394940": {"highway": "turning_circle"}, "261560555": {"highway": "turning_circle"}, "57904240": {"highway": "turning_circle"}, "262919892": {"highway": "turning_circle"}, "262920398": {"highway": "turning_circle"}, "263576435": {"highway": "turning_circle"}, "263576449": {"highway": "turning_circle"}, "263576450": {"highway": "turning_circle"}, "263576457": {"highway": "turning_circle"}, "263964562": {"highway": "turning_circle"}, "266573222": {"highway": "turning_circle"}, "266717164": {"highway": "turning_circle"}, "65434946": {"highway": "turning_circle"}, "266880514": {"highway": "turning_circle"}, "410839092": {"highway": "turning_circle"}, "904900907": {"highway": "turning_circle"}, "267795897": {"highway": "turning_circle"}, "275511833": {"highway": "turning_circle"}, "441572811": {"highway": "turning_circle"}, "276549390": {"highway": "turning_circle"}, "296886256": {"highway": "turning_circle"}, "65303514": {"highway": "turning_circle"}, "65309526": {"highway": "turning_circle"}, "65333841": {"highway": "turning_circle"}, "303229559": {"highway": "turning_circle"}, "303707030": {"highway": "turning_circle"}, "570569843": {"highway": "turning_circle"}, "110450718": {"highway": "turning_circle"}, "110450736": {"highway": "turning_circle"}, "612025486": {"highway": "turning_circle"}, "65327350": {"highway": "turning_circle"}, "65316502": {"highway": "turning_circle"}, "4044930438": {"highway": "turning_circle"}, "65504234": {"highway": "turning_circle"}, "339301852": {"highway": "turning_circle"}, "344386154": {"highway": "turning_circle"}, "65330704": {"highway": "turning_circle"}, "360162870": {"highway": "turning_circle"}, "1050139923": {"highway": "turning_circle"}, "1050139918": {"highway": "turning_circle"}, "360976440": {"highway": "turning_circle"}, "65479774": {"highway": "turning_circle"}, "370871735": {"highway": "turning_circle"}, "65295895": {"highway": "turning_circle"}, "388004001": {"highway": "turning_circle"}, "410838908": {"highway": "turning_circle"}, "410847362": {"highway": "turning_circle"}, "110414556": {"highway": "turning_circle"}, "414732918": {"highway": "turning_circle"}, "414900046": {"highway": "turning_circle"}, "414921965": {"highway": "turning_circle"}, "423748901": {"highway": "turning_circle"}, "429192070": {"highway": "turning_circle"}, "435111803": {"highway": "turning_circle"}, "493911526": {"highway": "turning_circle"}, "338884265": {"highway": "turning_circle"}, "57896011": {"highway": "turning_circle"}, "4044911320": {"highway": "turning_circle"}, "581074075": {"highway": "turning_circle"}, "2624398928": {"highway": "turning_circle"}, "65373710": {"highway": "turning_circle"}, "65312309": {"highway": "turning_circle"}, "65349063": {"highway": "turning_circle"}, "615143822": {"highway": "turning_circle"}, "633361220": {"highway": "turning_circle"}, "652406951": {"highway": "turning_circle"}, "65395982": {"highway": "turning_circle"}, "65360596": {"highway": "turning_circle"}, "65354408": {"highway": "turning_circle"}, "919450045": {"highway": "turning_circle"}, "976457881": {"highway": "turning_circle"}, "976457922": {"highway": "turning_circle"}, "976457928": {"highway": "turning_circle"}, "976457938": {"highway": "turning_circle"}, "1040542910": {"highway": "turning_circle"}, "2500126148": {"highway": "turning_circle"}, "110392859": {"highway": "turning_circle"}, "110422113": {"highway": "turning_circle"}, "1055915242": {"highway": "turning_circle"}, "110417801": {"highway": "turning_circle"}, "368391098": {"highway": "turning_circle"}, "110441556": {"highway": "turning_circle"}, "110441582": {"highway": "turning_circle"}, "3809271102": {"highway": "turning_circle"}, "65461461": {"highway": "turning_circle"}, "110377050": {"highway": "turning_circle"}, "110417738": {"highway": "turning_circle"}, "110417746": {"highway": "turning_circle"}, "1075508403": {"highway": "turning_circle"}, "110376349": {"highway": "turning_circle"}, "110383171": {"highway": "turning_circle"}, "1075678458": {"highway": "turning_circle"}, "110382452": {"highway": "turning_circle"}, "110381837": {"highway": "turning_circle"}, "1077416408": {"highway": "turning_circle"}, "110439988": {"highway": "turning_circle"}, "1079029695": {"highway": "turning_circle"}, "1249019400": {"highway": "turning_circle"}, "1682329672": {"highway": "turning_circle"}, "65337310": {"highway": "turning_circle"}, "370813693": {"highway": "turning_circle"}, "1377436537": {"highway": "turning_circle"}, "1286947308": {"highway": "turning_circle"}, "267292689": {"highway": "turning_circle"}, "267292688": {"highway": "turning_circle"}, "259337315": {"highway": "turning_circle"}, "259337318": {"highway": "turning_circle"}, "65431634": {"highway": "turning_circle"}, "667527951": {"highway": "turning_circle"}, "274406620": {"highway": "turning_circle"}, "418584220": {"highway": "turning_circle"}, "65358552": {"highway": "turning_circle"}, "275511794": {"highway": "turning_circle"}, "1286947313": {"highway": "turning_circle"}, "342512685": {"highway": "turning_circle"}, "65309729": {"highway": "turning_circle"}, "65340272": {"highway": "turning_circle"}, "1748900786": {"highway": "turning_circle"}, "65518449": {"highway": "turning_circle"}, "65325725": {"highway": "turning_circle"}, "1460324040": {"highway": "turning_circle"}, "65357033": {"highway": "turning_circle"}, "65295556": {"highway": "turning_circle"}, "65349439": {"highway": "turning_circle"}, "2374614261": {"highway": "turning_circle"}, "65431440": {"highway": "turning_circle"}, "65431446": {"highway": "turning_circle"}, "65389195": {"highway": "turning_circle"}, "65320932": {"highway": "turning_circle"}, "2446072882": {"highway": "turning_circle"}, "2496850050": {"highway": "turning_circle"}, "2503330178": {"highway": "turning_circle"}, "65353781": {"highway": "turning_circle"}, "65297396": {"highway": "turning_circle"}, "252686676": {"highway": "turning_circle"}, "65484532": {"highway": "turning_circle"}, "312103424": {"highway": "turning_circle"}, "2697625316": {"highway": "turning_circle"}, "65493386": {"highway": "turning_circle"}, "2822358580": {"highway": "turning_circle"}, "243683497": {"highway": "turning_circle"}, "3163754578": {"highway": "turning_circle"}, "318204849": {"highway": "turning_circle"}, "260300951": {"highway": "turning_circle"}, "4422679220": {"highway": "turning_circle"}, "65327305": {"highway": "turning_circle"}, "65349145": {"highway": "turning_circle"}, "65349153": {"highway": "turning_circle"}, "426314358": {"highway": "turning_circle"}, "65308428": {"highway": "turning_circle"}, "4422679264": {"highway": "turning_circle"}, "4422679339": {"highway": "turning_circle"}, "4422679215": {"highway": "turning_circle"}, "4422679305": {"highway": "turning_circle"}, "4422679320": {"highway": "turning_circle"}, "4422679204": {"highway": "turning_circle"}, "4422679323": {"highway": "turning_circle"}, "4422679318": {"highway": "turning_circle"}, "4422679238": {"highway": "turning_circle"}, "4422679229": {"highway": "turning_circle"}, "4422679276": {"highway": "turning_circle"}, "4621414303": {"highway": "turning_circle"}, "65309690": {"highway": "turning_circle"}, "65296636": {"highway": "turning_circle"}, "4681311576": {"highway": "turning_circle"}, "4695759236": {"highway": "turning_circle"}, "4695759237": {"highway": "turning_circle"}, "4695759248": {"highway": "turning_circle"}, "65316552": {"highway": "turning_circle"}, "65357594": {"highway": "turning_circle"}, "4904175716": {"highway": "turning_circle"}, "65507818": {"highway": "turning_circle"}, "4911027968": {"highway": "turning_circle"}, "4944806493": {"highway": "turning_circle"}, "4944806508": {"highway": "turning_circle"}, "4944811664": {"highway": "turning_circle"}, "1068502300": {"highway": "turning_circle"}, "330601304": {"highway": "turning_circle"}, "65448770": {"highway": "turning_circle"}, "344386171": {"highway": "turning_circle"}, "65280373": {"highway": "turning_circle"}, "253282502": {"highway": "turning_circle"}, "253282503": {"highway": "turning_circle"}, "253282519": {"highway": "turning_circle"}, "5652939749": {"highway": "turning_circle"}, "65337886": {"highway": "turning_circle"}, "5916193848": {"highway": "turning_circle"}, "263576456": {"highway": "turning_circle"}, "263576438": {"highway": "turning_circle"}}